{
    "blocks": "#natures_spirit:kaolin",
    "mappings": {
        "arts_and_crafts:white_paintbrush": "natures_spirit:white_kaolin",
        "arts_and_crafts:light_gray_paintbrush": "natures_spirit:light_gray_kaolin",
        "arts_and_crafts:gray_paintbrush": "natures_spirit:gray_kaolin",
        "arts_and_crafts:black_paintbrush": "natures_spirit:black_kaolin",
        "arts_and_crafts:brown_paintbrush": "natures_spirit:brown_kaolin",
        "arts_and_crafts:red_paintbrush": "natures_spirit:red_kaolin",
        "arts_and_crafts:orange_paintbrush": "natures_spirit:orange_kaolin",
        "arts_and_crafts:yellow_paintbrush": "natures_spirit:yellow_kaolin",
        "arts_and_crafts:lime_paintbrush": "natures_spirit:lime_kaolin",
        "arts_and_crafts:green_paintbrush": "natures_spirit:green_kaolin",
        "arts_and_crafts:cyan_paintbrush": "natures_spirit:cyan_kaolin",
        "arts_and_crafts:light_blue_paintbrush": "natures_spirit:light_blue_kaolin",
        "arts_and_crafts:blue_paintbrush": "natures_spirit:blue_kaolin",
        "arts_and_crafts:purple_paintbrush": "natures_spirit:purple_kaolin",
        "arts_and_crafts:magenta_paintbrush": "natures_spirit:magenta_kaolin",
        "arts_and_crafts:pink_paintbrush": "natures_spirit:pink_kaolin",
        "arts_and_crafts:bleachdew_paintbrush": "natures_spirit:kaolin"
    }
}